scrape_simple/__init__.py
scrape_simple/cli.py
scrape_simple/src/HTMLPage.py
scrape_simple/src/MediaContent.py
scrape_simple/src/SiteContent.py
scrape_simple/src/TextPage.py
scrape_simple/src/TorManager.py
scrape_simple/src/WebScraper.py
scrape_simple/src/__init__.py
scrape_simple/src/utils.py
scrape_simple-0.1.3.dist-info/licenses/LICENSE
scrape_simple-0.1.3.dist-info/METADATA
scrape_simple-0.1.3.dist-info/WHEEL
scrape_simple-0.1.3.dist-info/entry_points.txt
scrape_simple-0.1.3.dist-info/top_level.txt
scrape_simple-0.1.3.dist-info/RECORD
