Metadata-Version: 2.4
Name: scrape_simple
Version: 0.1.3
Summary: A web scraper that uses Tor for anonymity and supports media extraction
Home-page: https://github.com/HMCorp-Fund/scrape_simple
Author: Anton Pavlenko
Author-email: apavlenko@hmcorp.fund
Classifier: Programming Language :: Python :: 3
Classifier: License :: OSI Approved :: MIT License
Classifier: Operating System :: OS Independent
Requires-Python: >=3.6
License-File: LICENSE
Requires-Dist: requests>=2.28.0
Requires-Dist: PySocks>=1.7.1
Requires-Dist: stem>=1.8.0
Requires-Dist: beautifulsoup4>=4.11.0
Requires-Dist: lxml>=4.9.0
Requires-Dist: tqdm>=4.66.0
Provides-Extra: russian
Requires-Dist: natasha>=1.6.0; extra == "russian"
Provides-Extra: ai
Requires-Dist: transformers>=4.25.0; extra == "ai"
Requires-Dist: pillow>=9.0.0; extra == "ai"
Requires-Dist: torch>=2.0.0; extra == "ai"
Dynamic: author
Dynamic: author-email
Dynamic: classifier
Dynamic: description
Dynamic: description-content-type
Dynamic: home-page
Dynamic: license-file
Dynamic: provides-extra
Dynamic: requires-dist
Dynamic: requires-python
Dynamic: summary
